setup_server.py
common/__init__.py
common/decos.py
common/descryptors.py
common/errors.py
common/metaclasses.py
common/utils.py
common/variables.py
logs/__init__.py
messenger_server_november.egg-info/PKG-INFO
messenger_server_november.egg-info/SOURCES.txt
messenger_server_november.egg-info/dependency_links.txt
messenger_server_november.egg-info/requires.txt
messenger_server_november.egg-info/top_level.txt
prj_logs/__init__.py
prj_logs/config_client_log.py
prj_logs/config_server_log.py
unit_tests/__init__.py