Metadata-Version: 2.1
Name: messenger-server-november
Version: 0.0.1
Summary: messenger_server_november
Home-page: UNKNOWN
Author: Luca Gatfanova
Author-email: gatfanova@yandex.ru
License: UNKNOWN
Platform: UNKNOWN
